<?xml version="1.0" encoding="UTF-8"?>
<!DOCTYPE default-apps SYSTEM "gnome-da-list.dtd">
<default-apps>
  <web-browsers>
    <web-browser>
      <name>gooroom-browser</name>
      <executable>gooroom</executable>
      <command>/usr/bin/gooroom %s</command>
      <icon-name>gooroom-browser</icon-name>
      <run-in-terminal>false</run-in-terminal>
      <netscape-remote>true</netscape-remote>
      <tab-command>/usr/bin/gooroom %s</tab-command>
      <win-command>/usr/bin/gooroom --new-window %s</win-command>
    </web-browser>
  </web-browsers>
</default-apps>
